{
  "canciones": [
    {
      "nombre": "Alone",
      "autor": "Alan",
      "generos": [],
      "duracion": "2:45",
      "single": true,
      "reproducciones": 400000
    },
    {
      "nombre": "Macarena",
      "autor": "nohay",
      "generos": [],
      "duracion": "2:10",
      "single": true,
      "reproducciones": 3
    },
    {
      "nombre": "Buleria",
      "autor": "Bisbal",
      "generos": [],
      "duracion": "3:10",
      "single": true,
      "reproducciones": 40000
    },
    {
      "nombre": "hola",
      "autor": "pedro",
      "generos": [],
      "duracion": "34",
      "single": false,
      "reproducciones": 123
    },
    {
      "nombre": "adios",
      "autor": "juan",
      "generos": [],
      "duracion": "57",
      "single": false,
      "reproducciones": 3524
    },
    {
      "nombre": "chao",
      "autor": "gustavo",
      "generos": [],
      "duracion": "789",
      "single": true,
      "reproducciones": 352
    }
  ]
}